{"students": [{"name": "Aaron", "title": "Senior Consultant, Platform Integrations"}, {"name": "Alexa", "title": "Senior Manager, Customer Success"}, {"name": "Apurva", "title": "Analyst, Business Intelligence"}, {"name": "Ayesha", "title": "Manager, Project Success"}, {"name": "David F.", "title": "Manager, Customer Success"}, {"name": "David M.", "title": "Senior Manager, Project Success"}, {"name": "Fion", "title": "Manager, Customer Success"}, {"name": "Grace", "title": "Senior Analyst, Customer Development"}, {"name": "Julia", "title": "Manager, Project Success"}, {"name": "Leah", "title": "Analyst, Business Intelligence"}, {"name": "Manu", "title": "Senior Consultant, Platform Integrations"}, {"name": "Mattie", "title": "Manager, Project Success"}, {"name": "Navneet", "title": "IT Support Specialist"}, {"name": "Talia", "title": "Senior Manager, Content Team"}, {"name": "Wilson", "title": "Manager, Customer Success"}, {"name": "Brian", "title": "Team Lead, Project Success"}, {"name": "Chloe", "title": "Analyst, Customer Development"}, {"name": "Jimmy", "title": "Lead, Platform Support"}], "trainers": ["Alex", "Hannah", "Justin", "Kyle", "Marcus", "Marina", "PJ", "Ben", "Eric", "Neil", "Steven"]}